dictionary/__init__.py
dictionary/dictionary.py
furkan_baskaya_453_hw1-2.0.1.dist-info/METADATA
furkan_baskaya_453_hw1-2.0.1.dist-info/WHEEL
furkan_baskaya_453_hw1-2.0.1.dist-info/top_level.txt
furkan_baskaya_453_hw1-2.0.1.dist-info/RECORD
